{
    "15b79700-6673-454c-9808-560ffc5dffdc": {
        "email": "harry.davis3003@gmail.com",
        "fName": "Harry",
        "lName": "Davis",
        "status": "TES1"
    },
    "36a5c4d6-49b7-481b-a3d4-e3b82e3f8785": {
        "email": "harry.davis3003@gmail.com",
        "fName": "Harry",
        "lName": "Davis",
        "status": "OUT"
    },
    "61198ac6-bb87-46dd-9c2d-7ae3659186cf": {
        "email": "harry.davis3003@gmail.com",
        "fName": "Harry",
        "lName": "Davis",
        "status": "OUT"
    },
    "659ca251-a599-4587-ab7f-034cb816aa3a": {
        "email": "harry.davis3003@gmail.com",
        "fName": "Harry",
        "lName": "Davis",
        "status": "OUT"
    },
    "8c993b6c-1e4f-44ee-b92d-09f079f06cf7": {
        "email": "harry.davis3003@gmail.com",
        "fName": "Harry",
        "lName": "Davis",
        "status": "OUT"
    },
    "915f841a-9c26-41b1-b02b-14c3c55911a0": {
        "email": "harry.davis3003@gmail.com",
        "fName": "Harry",
        "lName": "Davis",
        "status": "OUT"
    },
    "cdf7c8b1-b3a4-475c-a37b-383ebeb0d458": {
        "email": "harry.davis3003@gmail.com",
        "fName": "Harry",
        "lName": "Davis",
        "status": "OUT"
    },
    "d5d5abf5-b18c-4b8b-9fe8-6434ae929d29": {
        "email": "james@mail.com",
        "fName": "JamesA",
        "lName": "Person",
        "status": "OUT"
    }
}